data_cliff/__init__.py
data_cliff/arg_parse.py
data_cliff/cli.py
data_cliff/data_cliff.py
data_cliff/getter.py
data_cliff/py.typed
data_cliff-0.1.3.dist-info/AUTHORS.rst
data_cliff-0.1.3.dist-info/LICENSE
data_cliff-0.1.3.dist-info/METADATA
data_cliff-0.1.3.dist-info/WHEEL
data_cliff-0.1.3.dist-info/entry_points.txt
data_cliff-0.1.3.dist-info/top_level.txt
data_cliff-0.1.3.dist-info/RECORD
