Metadata-Version: 2.1
Name: data-cliff
Version: 0.1.3
Summary: CLI tool to show differences on text data tracked by dvc.
Home-page: https://github.com/ruizdesotto/data_cliff
Author: Miguel Ruiz
Author-email: miguel.ruizdesotto@gmail.com
License: Apache Software License 2.0
Keywords: data_cliff
Classifier: Development Status :: 2 - Pre-Alpha
Classifier: Intended Audience :: Developers
Classifier: License :: OSI Approved :: Apache Software License
Classifier: Natural Language :: English
Classifier: Programming Language :: Python :: 3
Classifier: Programming Language :: Python :: 3.8
Classifier: Programming Language :: Python :: 3.9
Classifier: Programming Language :: Python :: 3.10
Requires-Python: >=3.6
License-File: LICENSE
License-File: AUTHORS.rst
